pyknioutReward/__init__.py
pyknioutReward/code_check.py
pyknioutReward/config.py
pyknioutReward/main.py
pykniout_reward-0.0.1.dist-info/LICENSE.txt
pykniout_reward-0.0.1.dist-info/METADATA
pykniout_reward-0.0.1.dist-info/WHEEL
pykniout_reward-0.0.1.dist-info/top_level.txt
pykniout_reward-0.0.1.dist-info/RECORD
